pyregexp/__init__.py
pyregexp/engine.py
pyregexp/lexer.py
pyregexp/match.py
pyregexp/pyrser.py
pyregexp/re_ast.py
pyregexp/tokens.py
pyregexp-0.3.1.dist-info/LICENSE
pyregexp-0.3.1.dist-info/METADATA
pyregexp-0.3.1.dist-info/WHEEL
pyregexp-0.3.1.dist-info/top_level.txt
pyregexp-0.3.1.dist-info/RECORD
