Metadata-Version: 2.1
Name: pyregexp
Version: 0.3.1
Summary: Simple regex library
Home-page: https://github.com/lorenzofelletti/pyregex
Download-URL: https://github.com/lorenzofelletti/pyregex/archive/v0.3.1.tar.gz
Author: Lorenzo Felletti
License: MIT
Keywords: regex,regexp,engine
Platform: UNKNOWN
Classifier: Development Status :: 3 - Alpha
Classifier: Intended Audience :: Developers
Classifier: Operating System :: OS Independent
Classifier: Topic :: Scientific/Engineering :: Information Analysis
Classifier: Topic :: Software Development :: Libraries :: Python Modules
Classifier: Topic :: Text Processing
Classifier: Topic :: Text Processing :: General
Classifier: License :: OSI Approved :: MIT License
Classifier: Programming Language :: Python :: 3
Classifier: Programming Language :: Python :: 3.8
Classifier: Programming Language :: Python :: 3.9
Classifier: Programming Language :: Python :: 3.10
License-File: LICENSE
